hammit/__init__.py
hammit/distance.py
hammit-1.0.2.dist-info/LICENSE
hammit-1.0.2.dist-info/METADATA
hammit-1.0.2.dist-info/WHEEL
hammit-1.0.2.dist-info/top_level.txt
hammit-1.0.2.dist-info/RECORD
